pydeserialize/__init__.py
pydeserialize/encoded.py
pydeserialize/pydeserialize.py
pydeserialize/run.py
pydeserialize-0.1.0.dist-info/LICENSE
pydeserialize-0.1.0.dist-info/METADATA
pydeserialize-0.1.0.dist-info/WHEEL
pydeserialize-0.1.0.dist-info/entry_points.txt
pydeserialize-0.1.0.dist-info/RECORD
