Metadata-Version: 2.1
Name: pydeserialize
Version: 0.1.0
Summary: Desserialização insegura em python
Home-page: https://github.com/joaoviictorti/pyserialize
License: MIT
Author: João
Author-email: joaovictorti08@gmail.com
Requires-Python: >=3.11,<4.0
Classifier: License :: OSI Approved :: MIT License
Classifier: Programming Language :: Python :: 3
Classifier: Programming Language :: Python :: 3.11
Requires-Dist: termcolor (>=2.3.0,<3.0.0)
